newr/__about__.py
newr/__init__.py
newr/file_types.py
newr/newr.py
newr-0.4.0.dist-info/METADATA
newr-0.4.0.dist-info/WHEEL
newr-0.4.0.dist-info/entry_points.txt
newr-0.4.0.dist-info/licenses/LICENSE.txt
newr-0.4.0.dist-info/RECORD
