Metadata-Version: 2.4
Name: newr
Version: 0.4.0
Summary: Select files by modification time with kind filtering and flexible ordering.
Project-URL: Homepage, https://github.com/tos-kamiya/newr
Project-URL: Repository, https://github.com/tos-kamiya/newr
Project-URL: Issues, https://github.com/tos-kamiya/newr/issues
Author-email: Toshihiro Kamiya <kamiya@mbj.nifty.com>
License: MIT License
License-File: LICENSE.txt
Keywords: cli,files,mtime,selector,utility
Classifier: Development Status :: 4 - Beta
Classifier: Environment :: Console
Classifier: Intended Audience :: End Users/Desktop
Classifier: License :: OSI Approved :: MIT License
Classifier: Operating System :: OS Independent
Classifier: Programming Language :: Python :: 3.10
Classifier: Programming Language :: Python :: 3.11
Classifier: Programming Language :: Python :: 3.12
Classifier: Programming Language :: Python :: Implementation :: CPython
Classifier: Topic :: Utilities
Requires-Python: >=3.10
Requires-Dist: python-magic
